autosmith/__init__.py
autosmith/docker.py
autosmith/env.py
autosmith/func.py
autosmith/smith.py
autosmith/store.py
autosmith/template.py
autosmith/version.py
autosmith/templates/Dockerfile.jinja
autosmith/templates/main.py.jinja
autosmith/templates/requirements.txt.jinja
autosmith-0.0.2.dist-info/LICENSE
autosmith-0.0.2.dist-info/METADATA
autosmith-0.0.2.dist-info/WHEEL
autosmith-0.0.2.dist-info/top_level.txt
autosmith-0.0.2.dist-info/RECORD
